{
  "topics": [
    {
      "id": "114-ko-society-대리모",
      "keyword": "대리모",
      "category": "society",
      "lang": "ko",
      "priority": 5,
      "status": "completed",
      "created_at": "2026-01-22T01:48:08.506572",
      "retry_count": 0,
      "keyword_type": "trend",
      "search_intent": "대리모 출산을 둘러싼 진실을 알지 못하면 잘못된 인식을 갖게 될 수 있다",
      "angle": "유명인의 대리모 출산 연출과 사회적 메시지 왜곡",
      "competition_level": "low",
      "references": [
        {
          "title": "옷 벗고 머리 산발…대리모 출산인데 '눈물 인증샷' 올린 팝스타 - 머니투데이",
          "url": "https://www.mt.co.kr/entertainment/2026/01/21/2026012116565122243",
          "source": "www.mt.co.kr"
        },
        {
          "title": "대리모로 딸 가진 女가수…‘상의 탈의’ 눈물 인증샷에 “작위적” 논란 : zum 뉴스",
          "url": "https://news.zum.com/articles/103548246/%EB%8C%80%EB%A6%AC%EB%AA%A8%EB%A1%9C-%EB%94%B8-%EA%B0%80%EC%A7%84-%EA%B0%80%EC%88%98-%EC%83%81%EC%9D%98-%ED%83%88%EC%9D%98-%EB%88%88%EB%AC%BC-%EC%9D%B8%EC%A6%9D%EC%83%B7%EC%97%90-%EC%9E%91%EC%9C%84%EC%A0%81-%EB%85%BC%EB%9E%80?cm=news_home_rank_article",
          "source": "news.zum.com"
        }
      ],
      "expiry_days": 3,
      "reserved_at": "2026-01-21T16:48:57.668000+00:00",
      "completed_at": "2026-01-21T17:26:51.754830+00:00"
    },
    {
      "id": "115-ko-entertainment-전민기",
      "keyword": "전민기",
      "category": "entertainment",
      "lang": "ko",
      "priority": 5,
      "status": "completed",
      "created_at": "2026-01-22T01:48:08.506579",
      "retry_count": 0,
      "keyword_type": "trend",
      "search_intent": "연예인의 부적절한 발언을 방치하면 사회적 가치관이 왜곡될 수 있다",
      "angle": "예능 프로그램의 자극적 콘텐츠와 사회적 책임 문제",
      "competition_level": "low",
      "references": [
        {
          "title": "전남편과 잠자리하는 여자 [낯박살고민센터 EP.15 사연별 다시보기] #전민기 #이지선 #조은나래 # 강민경 #김기혁 - YouTube",
          "url": "https://www.youtube.com/watch?v=oKbsk7dvFcc",
          "source": "www.youtube.com"
        },
        {
          "title": "전유성 - 위키백과, 우리 모두의 백과사전",
          "url": "https://ko.wikipedia.org/wiki/%EC%A0%84%EC%9C%A0%EC%84%B1",
          "source": "ko.wikipedia.org"
        }
      ],
      "expiry_days": 3,
      "reserved_at": "2026-01-21T16:48:57.668000+00:00",
      "completed_at": "2026-01-21T17:28:09.588482+00:00"
    },
    {
      "id": "119-ja-lifestyle-しゃぶ葉",
      "keyword": "しゃぶ葉",
      "category": "lifestyle",
      "lang": "ja",
      "priority": 5,
      "status": "completed",
      "created_at": "2026-01-22T01:48:08.506606",
      "retry_count": 0,
      "keyword_type": "trend",
      "search_intent": "企業マーケティングの問題点を把握しないと消費者として間違った選択をする",
      "angle": "企業コラボレーションの商業主義的側面と消費者軽視問題",
      "competition_level": "low",
      "references": [
        {
          "title": "アッキー：しゃぶ葉",
          "url": "https://ameblo.jp/umibouzu51/entry-12953209482.html",
          "source": "ameblo.jp"
        },
        {
          "title": "しゃぶ葉、リュウジさん＆安元洋貴さんとコラボ「背徳 至高のグルメフェア」を実施",
          "url": "https://gourmet.watch.impress.co.jp/docs/news/2079600.html",
          "source": "gourmet.watch.impress.co.jp"
        }
      ],
      "expiry_days": 3,
      "reserved_at": "2026-01-21T16:48:57.668000+00:00",
      "completed_at": "2026-01-21T17:29:23.457368+00:00"
    },
    {
      "id": "120-ja-entertainment-SixTONES",
      "keyword": "SixTONES",
      "category": "entertainment",
      "lang": "ja",
      "priority": 4,
      "status": "pending",
      "created_at": "2026-01-22T01:48:08.506613",
      "retry_count": 0,
      "keyword_type": "trend",
      "search_intent": "推しグループの方向性を把握しないとファン活動での失望や損失につながる",
      "angle": "アイドル産業の商業化とファンとの感情的距離の拡大",
      "competition_level": "low",
      "references": [
        {
          "title": "Single Collection - Album by SixTONES | Spotify",
          "url": "https://open.spotify.com/album/6sNdI5cR8tN2HJYYriaM1i",
          "source": "open.spotify.com"
        },
        {
          "title": "SixTONES – ベストアルバム「MILESixTONES -Best Tracks-」初回盤A・B Bonus Track digeST - YouTube",
          "url": "https://www.youtube.com/watch?v=Tgsd4Vn3ZUE",
          "source": "www.youtube.com"
        }
      ],
      "expiry_days": 3
    },
    {
      "id": "123-en-lifestyle-james-beard-semifina",
      "keyword": "james beard semifinalists 2026",
      "category": "lifestyle",
      "lang": "en",
      "priority": 5,
      "status": "pending",
      "created_at": "2026-01-22T01:48:08.506633",
      "retry_count": 0,
      "keyword_type": "trend",
      "search_intent": "Understanding award bias helps identify truly exceptional dining experiences before they're discovered",
      "angle": "Disconnect between award recognition and actual culinary excellence",
      "competition_level": "low",
      "references": [
        {
          "title": "The James Beard 2026 restaurant and chef award semifinalists list is out. Here are the region’s nomi",
          "url": "https://www.bostonglobe.com/2026/01/21/lifestyle/2026-new-england-james-beard-award-semifinalists-new-england/",
          "source": "www.bostonglobe.com"
        },
        {
          "title": "Meet the James Beard Foundation chef, restaurant semifinalists in 2026",
          "url": "https://eu.usatoday.com/story/entertainment/dining/2026/01/21/nominations-james-beard-awards-chef-restaurant-list/88270105007/",
          "source": "eu.usatoday.com"
        }
      ],
      "expiry_days": 3
    },
    {
      "id": "124-ko-business-진에어",
      "keyword": "진에어",
      "category": "business",
      "lang": "ko",
      "priority": 8,
      "status": "pending",
      "created_at": "2026-01-22T02:46:18.383830",
      "retry_count": 0,
      "keyword_type": "trend",
      "search_intent": "진에어 적자 소식으로 인한 항공료 인상이나 노선 변경 가능성을 확인하지 않으면 예약한 항공편이 취소되거나 추가 비용을 부담할 수 있음",
      "angle": "진에어의 재정 악화가 소비자에게 미치는 직접적 영향과 대안 항공사 비교",
      "competition_level": "medium",
      "references": [
        {
          "title": "진에어, 3년 만에 적자 전환…고환율·운임 하락에 수익성 악화 | 서울경제",
          "url": "https://www.sedaily.com/NewsView/2K7D4TP7PF",
          "source": "www.sedaily.com"
        },
        {
          "title": "진에어, 지난해 영업손실 163억원…3년 만에 적자 전환 - 뉴스1",
          "url": "https://www.news1.kr/industry/general-industry/6043789",
          "source": "www.news1.kr"
        }
      ],
      "expiry_days": 3
    }
  ]
}